textconf/__init__.py
textconf/config.py
textconf/enum.py
textconf/py.typed
textconf/render.py
textconf/template.py
textconf/testing.py
textconf-0.3.3.dist-info/WHEEL
textconf-0.3.3.dist-info/METADATA
textconf-0.3.3.dist-info/RECORD
