Metadata-Version: 2.3
Name: textconf
Version: 0.3.3
Summary: Jinja2-based text generation from configuration objects
Author: daizutabi
Author-email: daizutabi <daizutabi@gmail.com>
License: MIT License
Classifier: Development Status :: 4 - Beta
Classifier: Programming Language :: Python
Classifier: Programming Language :: Python :: 3.10
Classifier: Programming Language :: Python :: 3.11
Classifier: Programming Language :: Python :: 3.12
Classifier: Programming Language :: Python :: 3.13
Classifier: Programming Language :: Python :: 3.14
Requires-Dist: jinja2
Requires-Dist: omegaconf
Requires-Python: >=3.10
Project-URL: Documentation, https://daizutabi.github.io/textconf/
Project-URL: Issues, https://github.com/daizutabi/textconf/issues
Project-URL: Source, https://github.com/daizutabi/textconf
